sleep_inhibitor/__init__.py
sleep_inhibitor/__main__.py
sleep_inhibitor/sleep-inhibitor.conf
sleep_inhibitor/sleep-inhibitor.service
sleep_inhibitor/sleep_inhibitor.py
sleep_inhibitor/plugins/apk-running
sleep_inhibitor/plugins/is-alsa-playing
sleep_inhibitor/plugins/is-process-running
sleep_inhibitor/plugins/jellyfin-server
sleep_inhibitor/plugins/plex-media-server
sleep_inhibitor/plugins/ssh-session-open
sleep_inhibitor-1.25.dist-info/METADATA
sleep_inhibitor-1.25.dist-info/WHEEL
sleep_inhibitor-1.25.dist-info/entry_points.txt
sleep_inhibitor-1.25.dist-info/top_level.txt
sleep_inhibitor-1.25.dist-info/RECORD
