Metadata-Version: 2.4
Name: sleep-inhibitor
Version: 1.25
Summary: Program to run plugins to inhibit system sleep/suspend/hibernate
Author-email: Mark Blakeney <mark.blakeney@bullet-systems.net>
License-Expression: GPL-3.0-or-later
Project-URL: Homepage, https://github.com/bulletmark/sleep-inhibitor
Keywords: bash,systemd-inhibit,sleep,suspend,hibernate
Classifier: Programming Language :: Python :: 3
Requires-Python: >=3.7
Requires-Dist: ruamel.yaml
